promptguard/__init__.py
promptguard/client.py
promptguard/config.py
promptguard_sdk-1.2.0.dist-info/METADATA
promptguard_sdk-1.2.0.dist-info/WHEEL
promptguard_sdk-1.2.0.dist-info/RECORD
