Metadata-Version: 2.4
Name: promptguard-sdk
Version: 1.2.0
Summary: Drop-in security for AI applications - AI Firewall SDK
Project-URL: Homepage, https://promptguard.co
Project-URL: Documentation, https://docs.promptguard.co
Project-URL: Repository, https://github.com/acebot712/promptguard
Project-URL: Issues, https://github.com/acebot712/promptguard/issues
Author-email: PromptGuard <support@promptguard.co>
License-Expression: MIT
Keywords: ai,ai-firewall,ai-security,anthropic,llm,llm-security,openai,pii-detection,prompt-injection,security
Classifier: Development Status :: 4 - Beta
Classifier: Intended Audience :: Developers
Classifier: License :: OSI Approved :: MIT License
Classifier: Programming Language :: Python :: 3
Classifier: Programming Language :: Python :: 3.8
Classifier: Programming Language :: Python :: 3.9
Classifier: Programming Language :: Python :: 3.10
Classifier: Programming Language :: Python :: 3.11
Classifier: Programming Language :: Python :: 3.12
Classifier: Topic :: Scientific/Engineering :: Artificial Intelligence
Classifier: Topic :: Security
Requires-Python: >=3.8
Requires-Dist: httpx>=0.24.0
Provides-Extra: dev
Requires-Dist: pytest-asyncio>=0.21.0; extra == 'dev'
Requires-Dist: pytest>=7.0.0; extra == 'dev'
Requires-Dist: ruff>=0.1.0; extra == 'dev'
